pyemc/__init__.py
pyemc/runner.py
pyemc/emc/HISTORY
pyemc/emc/LICENSE
pyemc/emc/README
pyemc/emc/bin/emc_linux_aarch64
pyemc/emc/bin/emc_linux_x86_64
pyemc/emc/bin/emc_macos
pyemc/emc/bin/emc_win32.exe
pyemc/emc/check/all.txt
pyemc/emc/check/check.pl
pyemc/emc/check/checked.txt
pyemc/emc/check/notes.txt
pyemc/emc/check/void_funcion_n.txt
pyemc/emc/docs/emc.pdf
pyemc/emc/examples/setup/chemistry/bulk/setup.esh
pyemc/emc/examples/setup/chemistry/field/charmm/chemistry.esh
pyemc/emc/examples/setup/chemistry/field/charmm/setup.sh
pyemc/emc/examples/setup/chemistry/field/charmm/solution.esh
pyemc/emc/examples/setup/chemistry/field/dpd/name.esh
pyemc/emc/examples/setup/chemistry/field/dpd/setup.sh
pyemc/emc/examples/setup/chemistry/field/generate/build.emc
pyemc/emc/examples/setup/chemistry/field/generate/field.esh
pyemc/emc/examples/setup/chemistry/field/generate/field.in
pyemc/emc/examples/setup/chemistry/field/generate/field.prm
pyemc/emc/examples/setup/chemistry/field/lj/field.esh
pyemc/emc/examples/setup/chemistry/field/opls/aa/name.esh
pyemc/emc/examples/setup/chemistry/field/opls/aa/setup.sh
pyemc/emc/examples/setup/chemistry/field/opls/ua/name.esh
pyemc/emc/examples/setup/chemistry/field/opls/ua/setup.sh
pyemc/emc/examples/setup/chemistry/field/opls/water/water.esh
pyemc/emc/examples/setup/chemistry/field/pcff/name.esh
pyemc/emc/examples/setup/chemistry/field/pcff/setup.sh
pyemc/emc/examples/setup/chemistry/field/trappe/name.esh
pyemc/emc/examples/setup/chemistry/field/trappe/setup.sh
pyemc/emc/examples/setup/chemistry/field/user/build.emc
pyemc/emc/examples/setup/chemistry/field/user/polymer.esh
pyemc/emc/examples/setup/chemistry/field/user/polymer.in
pyemc/emc/examples/setup/chemistry/field/user/polymer.prm
pyemc/emc/examples/setup/chemistry/field/user/polymer.top
pyemc/emc/examples/setup/chemistry/gromacs/setup.esh
pyemc/emc/examples/setup/chemistry/multiphase/multiphase.esh
pyemc/emc/examples/setup/chemistry/polymer/alternate/build.emc
emc_pypi-2025.8.21.dist-info/LICENSE
emc_pypi-2025.8.21.dist-info/METADATA
emc_pypi-2025.8.21.dist-info/WHEEL
emc_pypi-2025.8.21.dist-info/top_level.txt
emc_pypi-2025.8.21.dist-info/RECORD
