Metadata-Version: 2.1
Name: emc-pypi
Version: 2025.8.21
Summary: Python interface for the Enhanced Monte Carlo (EMC) package
Home-page: https://github.com/kevinshen56714/emc-pypi
Author: Kuan-Hsuan (Kevin) Shen
Author-email: kevinshen56714@gmail.com
License: UNKNOWN
Keywords: EMC,Molecular Dynamics,LAMMPS,SMILES,Simulation
Platform: UNKNOWN
Classifier: Programming Language :: Python :: 3
Classifier: Programming Language :: Python :: 3.7
Classifier: Programming Language :: Python :: 3.8
Classifier: Programming Language :: Python :: 3.9
Classifier: Programming Language :: Python :: 3.10
Classifier: Programming Language :: Python :: 3.11
Classifier: Programming Language :: Python :: 3.12
Classifier: Programming Language :: Python :: 3.13
Classifier: Operating System :: OS Independent
Classifier: Topic :: Software Development
Classifier: Topic :: Utilities
